fastapi_quickcrud_codegen/__init__.py
fastapi_quickcrud_codegen/crud_generator.py
fastapi_quickcrud_codegen/db_model.py
fastapi_quickcrud_codegen/generator/__init__.py
fastapi_quickcrud_codegen/generator/code_generator.py
fastapi_quickcrud_codegen/generator/common_module_template_generator.py
fastapi_quickcrud_codegen/generator/crud_template_generator.py
fastapi_quickcrud_codegen/generator/model_template_generator.py
fastapi_quickcrud_codegen/misc/__init__.py
fastapi_quickcrud_codegen/misc/constant.py
fastapi_quickcrud_codegen/misc/crud_model.py
fastapi_quickcrud_codegen/misc/exceptions.py
fastapi_quickcrud_codegen/misc/get_table_name.py
fastapi_quickcrud_codegen/misc/type.py
fastapi_quickcrud_codegen/model/__init__.py
fastapi_quickcrud_codegen/model/common_builder.py
fastapi_quickcrud_codegen/model/crud_builder.py
fastapi_quickcrud_codegen/model/model_builder.py
fastapi_quickcrud_codegen/model/template/Constant.jinja2
fastapi_quickcrud_codegen/model/template/Enum.jinja2
fastapi_quickcrud_codegen/model/template/__init__.py
fastapi_quickcrud_codegen/model/template/common/__init__.py
fastapi_quickcrud_codegen/model/template/common/api_route.jinja2
fastapi_quickcrud_codegen/model/template/common/app.jinja2
fastapi_quickcrud_codegen/model/template/common/db.jinja2
fastapi_quickcrud_codegen/model/template/common/http_exception.jinja2
fastapi_quickcrud_codegen/model/template/common/memory_sql_session.jinja2
fastapi_quickcrud_codegen/model/template/common/route_container.jinja2
fastapi_quickcrud_codegen/model/template/common/typing.jinja2
fastapi_quickcrud_codegen/model/template/common/utils.jinja2
fastapi_quickcrud_codegen/model/template/pydantic/BaseModel.jinja2
fastapi_quickcrud_codegen/model/template/pydantic/BaseModel_root.jinja2
fastapi_quickcrud_codegen/model/template/pydantic/Config.jinja2
fastapi_quickcrud_codegen/model/template/pydantic/__init__.py
fastapi_quickcrud_codegen/model/template/pydantic/base_model_paginate.jinja2
fastapi_crud_code_generator-0.0.31.dist-info/LICENSE
fastapi_crud_code_generator-0.0.31.dist-info/METADATA
fastapi_crud_code_generator-0.0.31.dist-info/WHEEL
fastapi_crud_code_generator-0.0.31.dist-info/top_level.txt
fastapi_crud_code_generator-0.0.31.dist-info/RECORD
