Metadata-Version: 2.1
Name: fastapi-crud-code-generator
Version: 0.0.31
Summary: FastaAPI's CRUD project generator for SQLALchemy.
Home-page: https://github.com/LuisLuii/fastapi-crud-template-generator
Author: Luis Lui
Author-email: luis11235178@gmail.com
License: MIT License
Keywords: fastapi,crud,restful,routing,SQLAlchemy,generator,crudrouter,postgresql,builder
Classifier: Operating System :: OS Independent
Classifier: Programming Language :: Python
Classifier: Topic :: Software Development :: Code Generators
Classifier: Typing :: Typed
Classifier: Development Status :: 5 - Production/Stable
Classifier: Environment :: Web Environment
Classifier: Framework :: FastAPI
Classifier: License :: OSI Approved :: MIT License
Classifier: Programming Language :: Python :: 3 :: Only
Classifier: Programming Language :: Python :: 3.7
Classifier: Programming Language :: Python :: 3.8
Classifier: Programming Language :: Python :: 3.9
Classifier: Programming Language :: Python :: 3.10
Classifier: Topic :: Internet :: WWW/HTTP :: HTTP Servers
Classifier: Topic :: Internet :: WWW/HTTP
Requires-Python: >=3.7
License-File: LICENSE
Requires-Dist: aiosqlite <=0.17.0
Requires-Dist: asyncpg <=0.26.0
Requires-Dist: fastapi <=0.85.1
Requires-Dist: greenlet <=1.1.3.post0
Requires-Dist: Jinja2 <=3.1.2
Requires-Dist: psycopg2 <=2.9.4
Requires-Dist: pydantic <=1.10.2
Requires-Dist: SQLAlchemy <=1.4.42
Requires-Dist: StrEnum <=0.4.8
Requires-Dist: uvicorn <=0.19.0
